automize_science/__init__.py
automize_science/computing_statistics.py
automize_science/data_cleanup.py
automize_science/graph_constructor.py
automize_science/saving.py
automize_science/workflows.py
automize_science-1.0.2.dist-info/LICENSE
automize_science-1.0.2.dist-info/WHEEL
automize_science-1.0.2.dist-info/METADATA
automize_science-1.0.2.dist-info/RECORD
