Metadata-Version: 2.1
Name: automize_science
Version: 1.0.2
Summary: Automize Science is a Python package designed to elaborate data into graphs coming from lipid extractions (LC/MS).
Author-email: Elide Brunelli <elide.98@gmail.com>
Classifier: License :: OSI Approved :: MIT License
Requires-Dist: numpy~=2.0
Requires-Dist: pandas~=2.0
Requires-Dist: openpyxl~=3.1
Requires-Dist: scipy~=1.13
Requires-Dist: matplotlib~=3.9
Requires-Dist: seaborn~=0.13
Requires-Dist: starbars~=1.0
Project-URL: Home, https://github.com/elide-b/automize-science
